hai_client/__init__.py
hai_client/version.py
hai_client/apis/__init__.py
hai_client/apis/python_api.py
hepai_client-1.0.3.dist-info/METADATA
hepai_client-1.0.3.dist-info/WHEEL
hepai_client-1.0.3.dist-info/top_level.txt
hepai_client-1.0.3.dist-info/RECORD
