Metadata-Version: 2.1
Name: hepai-client
Version: 1.0.3
Summary: The Client for High energy phscis Artificial Intelligence plateform, HAI.
Home-page: https://github.com/zhangzhengde0225/hai-client
Author: Zhengde Zhang
Author-email: zdzhang@163.com
License: MIT
Platform: UNKNOWN
Classifier: License :: OSI Approved :: MIT License
Classifier: Programming Language :: Python
Classifier: Programming Language :: Python :: 3
Classifier: Programming Language :: Python :: 3.6
Classifier: Programming Language :: Python :: Implementation :: CPython
Classifier: Programming Language :: Python :: Implementation :: PyPy
Requires-Python: >=3.6.0
